stoqdrivers/__init__.py
stoqdrivers/abicomp.py
stoqdrivers/base.py
stoqdrivers/conf/bematech.ini
stoqdrivers/conf/dataregis.ini
stoqdrivers/conf/perto.ini
stoqdrivers/configparser.py
stoqdrivers/constants.py
stoqdrivers/devices/__init__.py
stoqdrivers/enum.py
stoqdrivers/escp.py
stoqdrivers/escpos.py
stoqdrivers/exceptions.py
stoqdrivers/interfaces.py
stoqdrivers/locale/POTFILES.list
stoqdrivers/locale/es_ES/LC_MESSAGES/stoqdrivers.po
stoqdrivers/locale/pt_BR/LC_MESSAGES/stoqdrivers.po
stoqdrivers/locale/stoqdrivers.pot
stoqdrivers/printers/__init__.py
stoqdrivers/printers/base.py
stoqdrivers/printers/bematech/DP20C.py
stoqdrivers/printers/bematech/MP20.py
stoqdrivers/printers/bematech/MP2100.py
stoqdrivers/printers/bematech/MP2100TH.py
stoqdrivers/printers/bematech/MP25.py
stoqdrivers/printers/bematech/MP4200TH.py
stoqdrivers/printers/bematech/__init__.py
stoqdrivers/printers/capabilities.py
stoqdrivers/printers/cheque.py
stoqdrivers/printers/daruma/DR700.py
stoqdrivers/printers/daruma/FS2100.py
stoqdrivers/printers/daruma/FS345.py
stoqdrivers/printers/daruma/FS600MFD.py
stoqdrivers/printers/daruma/__init__.py
stoqdrivers/printers/dataregis/EP375.py
stoqdrivers/printers/dataregis/Quick.py
stoqdrivers/printers/dataregis/__init__.py
stoqdrivers/printers/elgin/I9.py
stoqdrivers/printers/elgin/KFiscal.py
stoqdrivers/printers/elgin/__init__.py
stoqdrivers/printers/epson/FBII.py
stoqdrivers/printers/epson/FBIII.py
stoqdrivers/printers/epson/TMT20.py
stoqdrivers/printers/epson/TMT70.py
stoqdrivers/printers/epson/__init__.py
stoqdrivers/printers/fiscal.py
stoqdrivers/printers/fiscnet/FiscNetECF.py
stoqdrivers/printers/fiscnet/__init__.py
stoqdrivers/printers/nonfiscal.py
stoqdrivers/printers/perto/Pay2023.py
stoqdrivers/printers/perto/__init__.py
stoqdrivers/printers/snbc/BKC310.py
stoqdrivers/printers/snbc/__init__.py
stoqdrivers/printers/sweda/SI150.py
stoqdrivers/printers/sweda/SI300.py
stoqdrivers/printers/sweda/__init__.py
stoqdrivers/printers/tanca/TP650.py
stoqdrivers-2.1.0.dist-info/WHEEL
stoqdrivers-2.1.0.dist-info/METADATA
stoqdrivers-2.1.0.dist-info/RECORD
